django_httpolice/__init__.py
django_httpolice/__metadata__.py
django_httpolice/common.py
django_httpolice/middleware.py
django_httpolice/views.py
Django_HTTPolice-0.5.0.dist-info/LICENSE.txt
Django_HTTPolice-0.5.0.dist-info/METADATA
Django_HTTPolice-0.5.0.dist-info/WHEEL
Django_HTTPolice-0.5.0.dist-info/top_level.txt
Django_HTTPolice-0.5.0.dist-info/RECORD
