Metadata-Version: 2.1
Name: Django-HTTPolice
Version: 0.5.0
Summary: Django integration for HTTPolice
Home-page: https://github.com/vfaronov/django-httpolice
Author: Vasiliy Faronov
Author-email: vfaronov@gmail.com
License: MIT
Keywords: HTTP message request response standards RFC validator Django
Platform: UNKNOWN
Classifier: Framework :: Django
Classifier: Intended Audience :: Developers
Classifier: License :: OSI Approved :: MIT License
Classifier: Programming Language :: Python :: 3
Classifier: Programming Language :: Python :: 3 :: Only
Classifier: Programming Language :: Python :: 3.4
Classifier: Programming Language :: Python :: 3.5
Classifier: Programming Language :: Python :: 3.6
Classifier: Programming Language :: Python :: 3.7
Classifier: Programming Language :: Python :: Implementation :: CPython
Classifier: Programming Language :: Python :: Implementation :: PyPy
Classifier: Topic :: Internet :: WWW/HTTP
Classifier: Topic :: Software Development :: Quality Assurance
Requires-Python: >= 3.4
Requires-Dist: Django (>=1.11.0)
Requires-Dist: HTTPolice (>=0.4.0)
